keelib/__init__.py
keelib/encryptor.py
keelib/utils.py
keelib-0.1.3.dist-info/LICENSE
keelib-0.1.3.dist-info/METADATA
keelib-0.1.3.dist-info/WHEEL
keelib-0.1.3.dist-info/top_level.txt
keelib-0.1.3.dist-info/RECORD
