Metadata-Version: 2.1
Name: keelib
Version: 0.1.3
Summary: KEE by Jaegerwald, but as a library.
Author: TheZoidMaster
Author-email: 
Project-URL: Source, https://github.com/TheZoidMaster/keelib
Project-URL: Original, https://github.com/JaegerwaldDev/KEE
Classifier: Programming Language :: Python :: 3
Classifier: Operating System :: OS Independent
Requires-Python: >=3.6
License-File: LICENSE
Requires-Dist: numpy
Requires-Dist: colorama
